Metadata-Version: 2.1
Name: strbuilder
Version: 1.1.3
Summary: A simple string builder
Home-page: https://github.com/am230/strbuilder
Author: am230
Author-email: am.230@outlook.jp
License: MIT Licence
Keywords: builder
Platform: any
License-File: LICENSE
